[
  {
    "id": "444055",
    "name": "EVENTO E$PN  ",
    "logo": "https://i.ibb.co/HqQRnp7/EVENTOSPPV.jpg",
    "category": "⚽ EVENTOS PREMIUM ⚽",
    "url": "http://daleplaytv.vip:80/live/Everardo4008/Everardo4008/444055.m3u8",
    "type": "live",
    "rating": "",
    "added": "1782112981"
  },
  {
    "id": "444067",
    "name": "EVENTO E$PN 2   ",
    "logo": "https://i.ibb.co/HqQRnp7/EVENTOSPPV.jpg",
    "category": "⚽ EVENTOS PREMIUM ⚽",
    "url": "http://daleplaytv.vip:80/live/Everardo4008/Everardo4008/444067.m3u8",
    "type": "live",
    "rating": "",
    "added": "1782112981"
  },
  {
    "id": "444058",
    "name": "EVENTO E$PN 3    ",
    "logo": "https://i.ibb.co/HqQRnp7/EVENTOSPPV.jpg",
    "category": "⚽ EVENTOS PREMIUM ⚽",
    "url": "http://daleplaytv.vip:80/live/Everardo4008/Everardo4008/444058.m3u8",
    "type": "live",
    "rating": "",
    "added": "1782112981"
  },
  {
    "id": "444064",
    "name": "EVENTO E$PN 4    ",
    "logo": "https://i.ibb.co/HqQRnp7/EVENTOSPPV.jpg",
    "category": "⚽ EVENTOS PREMIUM ⚽",
    "url": "http://daleplaytv.vip:80/live/Everardo4008/Everardo4008/444064.m3u8",
    "type": "live",
    "rating": "",
    "added": "1782112981"
  },
  {
    "id": "444061",
    "name": "EVENTO E$PN 5   ",
    "logo": "https://i.ibb.co/HqQRnp7/EVENTOSPPV.jpg",
    "category": "⚽ EVENTOS PREMIUM ⚽",
    "url": "http://daleplaytv.vip:80/live/Everardo4008/Everardo4008/444061.m3u8",
    "type": "live",
    "rating": "",
    "added": "1782112981"
  },
  {
    "id": "444070",
    "name": "EVENTO 6 D$PORTS     ",
    "logo": "https://i.ibb.co/HqQRnp7/EVENTOSPPV.jpg",
    "category": "⚽ EVENTOS PREMIUM ⚽",
    "url": "http://daleplaytv.vip:80/live/Everardo4008/Everardo4008/444070.m3u8",
    "type": "live",
    "rating": "",
    "added": "1782112981"
  },
  {
    "id": "444079",
    "name": "EVENTO 7   ",
    "logo": "https://i.ibb.co/HqQRnp7/EVENTOSPPV.jpg",
    "category": "⚽ EVENTOS PREMIUM ⚽",
    "url": "http://daleplaytv.vip:80/live/Everardo4008/Everardo4008/444079.m3u8",
    "type": "live",
    "rating": "",
    "added": "1782112981"
  },
  {
    "id": "444073",
    "name": "EVENTO 8 I ",
    "logo": "https://i.ibb.co/HqQRnp7/EVENTOSPPV.jpg",
    "category": "⚽ EVENTOS PREMIUM ⚽",
    "url": "http://daleplaytv.vip:80/live/Everardo4008/Everardo4008/444073.m3u8",
    "type": "live",
    "rating": "",
    "added": "1780621861"
  },
  {
    "id": "444297",
    "name": "EVENTO 9   ",
    "logo": "https://i.ibb.co/HqQRnp7/EVENTOSPPV.jpg",
    "category": "⚽ EVENTOS PREMIUM ⚽",
    "url": "http://daleplaytv.vip:80/live/Everardo4008/Everardo4008/444297.m3u8",
    "type": "live",
    "rating": "",
    "added": "1780141502"
  },
  {
    "id": "444300",
    "name": "EVENTO 10  ",
    "logo": "https://i.ibb.co/HqQRnp7/EVENTOSPPV.jpg",
    "category": "⚽ EVENTOS PREMIUM ⚽",
    "url": "http://daleplaytv.vip:80/live/Everardo4008/Everardo4008/444300.m3u8",
    "type": "live",
    "rating": "",
    "added": "1782112981"
  },
  {
    "id": "444524",
    "name": "EVENTO  11  ",
    "logo": "  https://i.ibb.co/HqQRnp7/EVENTOSPPV.jpg",
    "category": "⚽ EVENTOS PREMIUM ⚽",
    "url": "http://daleplaytv.vip:80/live/Everardo4008/Everardo4008/444524.m3u8",
    "type": "live",
    "rating": "",
    "added": "1780141502"
  },
  {
    "id": "444521",
    "name": "EVENTO 12    ",
    "logo": "  https://i.ibb.co/HqQRnp7/EVENTOSPPV.jpg",
    "category": "⚽ EVENTOS PREMIUM ⚽",
    "url": "http://daleplaytv.vip:80/live/Everardo4008/Everardo4008/444521.m3u8",
    "type": "live",
    "rating": "",
    "added": "1780141502"
  }
]