[
  {
    "id": "",
    "name": "RUN:TIME ACCIÓN",
    "logo": "http://flx.lat:8080/images/0f6883aafe18f5061f90db3c4f7470c4.jpg",
    "category": "✅ RUN TIME PLAY ",
    "url": "http://flexlive.lat:8080//live/dagopineda/DAeVXavdtYjx/272229.ts",
    "type": "live",
    "rating": "",
    "added": ""
  },
  {
    "id": "",
    "name": "RUN:TIME CURROJAIME",
    "logo": "http://flx.lat:8080/images/94eb0462b4c79466a491995e59c251fd.jpg",
    "category": "✅ RUN TIME PLAY ",
    "url": "http://flexlive.lat:8080//live/dagopineda/DAeVXavdtYjx/272230.ts",
    "type": "live",
    "rating": "",
    "added": ""
  },
  {
    "id": "",
    "name": "RUN:TIME A SANGRE FRIA",
    "logo": "http://flx.lat:8080/images/3259c9de7d86eb89e40ca7c45d124694.jpg",
    "category": "✅ RUN TIME PLAY ",
    "url": "http://flexlive.lat:8080//live/dagopineda/DAeVXavdtYjx/272232.ts",
    "type": "live",
    "rating": "",
    "added": ""
  },
  {
    "id": "",
    "name": "RUN : TIME CRIMEN",
    "logo": "http://flx.lat:8080/images/0b31449d2f0971b0091cbd6a423e7ad9.jpg",
    "category": "✅ RUN TIME PLAY ",
    "url": "http://flexlive.lat:8080//live/dagopineda/DAeVXavdtYjx/272234.ts",
    "type": "live",
    "rating": "",
    "added": ""
  },
  {
    "id": "",
    "name": "RUN :TIME CINE ESPANTO",
    "logo": "http://flx.lat:8080/images/27d653258bef9fde67292a3358837d1c.jpg",
    "category": "✅ RUN TIME PLAY ",
    "url": "http://flexlive.lat:8080//live/dagopineda/DAeVXavdtYjx/272235.ts",
    "type": "live",
    "rating": "",
    "added": ""
  },
  {
    "id": "",
    "name": "RUN : TIME PELICULAS",
    "logo": "http://flx.lat:8080/images/d6627314a84b7fd7f60246e8fd8da42b.jpg",
    "category": "✅ RUN TIME PLAY ",
    "url": "http://flexlive.lat:8080//live/dagopineda/DAeVXavdtYjx/272236.ts",
    "type": "live",
    "rating": "",
    "added": ""
  },
  {
    "id": "",
    "name": "RUN:TIME A SANGRE FRIA",
    "logo": "http://flx.lat:8080/images/3259c9de7d86eb89e40ca7c45d124694.jpg",
    "category": "✅ RUN TIME PLAY ",
    "url": "http://flexlive.lat:8080//live/dagopineda/DAeVXavdtYjx/272237.ts",
    "type": "live",
    "rating": "",
    "added": ""
  },
  {
    "id": "",
    "name": "RUN:TIME COMEDIA",
    "logo": "http://flx.lat:8080/images/5cb46a45fc526fd908ef21d4a01a13ba.jpg",
    "category": "✅ RUN TIME PLAY ",
    "url": "http://flexlive.lat:8080//live/dagopineda/DAeVXavdtYjx/272238.ts",
    "type": "live",
    "rating": "",
    "added": ""
  },
  {
    "id": "",
    "name": "RUN :TIME ROMANCE",
    "logo": "http://flx.lat:8080/images/3a74500f23449bc0da1059c648a5139d.jpg",
    "category": "✅ RUN TIME PLAY ",
    "url": "http://flexlive.lat:8080//live/dagopineda/DAeVXavdtYjx/273049.ts",
    "type": "live",
    "rating": "",
    "added": ""
  },
  {
    "id": "",
    "name": "RUN :TIME FAMILIA",
    "logo": "http://flx.lat:8080/images/55a2d85086495a6b5ba6e8f79374cac6.jpg",
    "category": "✅ RUN TIME PLAY ",
    "url": "http://flexlive.lat:8080//live/dagopineda/DAeVXavdtYjx/273050.ts",
    "type": "live",
    "rating": "",
    "added": ""
  },
  {
    "id": "",
    "name": "RUN :TIME C4 ALERTA",
    "logo": "http://flx.lat:8080/images/6d3a8b18a54c1b51e486aa9d5afc55d7.jpg",
    "category": "✅ RUN TIME PLAY ",
    "url": "http://flexlive.lat:8080//live/dagopineda/DAeVXavdtYjx/273051.ts",
    "type": "live",
    "rating": "",
    "added": ""
  }
]